scmagnify/GRNMuData.py
scmagnify/__init__.py
scmagnify/logo_min.png
scmagnify/requirements.txt
scmagnify/datasets/__init__.py
scmagnify/datasets/_datasets.py
scmagnify/external/differentiation_potential.py
scmagnify/external/plotting/__init__.py
scmagnify/external/plotting/_plot1cell.py
scmagnify/external/plotting/liana.py
scmagnify/logging/__init__.py
scmagnify/logging/_logging.py
scmagnify/models/__init__.py
scmagnify/models/_modules.py
scmagnify/models/_train.py
scmagnify/models/_utils.py
scmagnify/plotting/__init__.py
scmagnify/plotting/_barplot.py
scmagnify/plotting/_cell_state_select.py
scmagnify/plotting/_circosplot.py
scmagnify/plotting/_distplot.py
scmagnify/plotting/_docs.py
scmagnify/plotting/_dumbbellplot.py
scmagnify/plotting/_genome_viewer.py
scmagnify/plotting/_grn_visualizer.py
scmagnify/plotting/_heatmap.py
scmagnify/plotting/_network_plot.py
scmagnify/plotting/_palettes.py
scmagnify/plotting/_rankplot.py
scmagnify/plotting/_scatter.py
scmagnify/plotting/_seqlogo.py
scmagnify/plotting/_stripplot.py
scmagnify/plotting/_test_assoc.py
scmagnify/plotting/_trendplot.py
scmagnify/plotting/_utils.py
scmagnify/plotting/docs.py
scmagnify/preprocess/__init__.py
scmagnify/preprocess/basic.py
scmagnify/settings/__init__.py
scmagnify/settings/_info.py
scmagnify/settings/_settings.py
scmagnify/tools/__init__.py
scmagnify/tools/_basal_grn.py
scmagnify/tools/_cell_state_select.py
scmagnify/tools/_func_enrich.py
scmagnify/tools/_gene_activity.py
scmagnify/tools/_intracci.py
scmagnify/tools/_metacell.py
scmagnify/tools/_motif_scan.py
scmagnify/tools/_net_stat.py
scmagnify/tools/_parallelize.py
scmagnify/tools/_peak_gene_corr.py
scmagnify/tools/_tensor_decomp.py
scmagnify/tools/_test_assoc.py
scmagnify/tools/_trace_gene_select.py
scmagnify/tools/_utils.py
scmagnify/utils/__init__.py
scmagnify/utils/_docs.py
scmagnify/utils/_package_version_checker.py
scmagnify/utils/_progress.py
scmagnify/utils/_utils.py
scmagnify-0.1.1.dist-info/METADATA
scmagnify-0.1.1.dist-info/WHEEL
scmagnify-0.1.1.dist-info/licenses/LICENSE
scmagnify-0.1.1.dist-info/RECORD
