Metadata-Version: 2.4
Name: scmagnify
Version: 0.1.1
Summary: scMagnify is a versatile Python toolkit for inferring and analyzing gene regulatory networks (GRNs) from single-cell multi-omic datasets
Project-URL: Documentation, https://scMagnify.readthedocs.io/
Project-URL: Homepage, https://github.com/xfchen0912/scMagnify
Project-URL: Source, https://github.com/xfchen0912/scMagnify
Author: Xufeng Chen
Maintainer-email: Xufeng Chen <chenxufeng2022@sinh.ac.cn>
License: BSD 3-Clause License
License-File: LICENSE
Classifier: Programming Language :: Python :: 3 :: Only
Classifier: Programming Language :: Python :: 3.10
Classifier: Programming Language :: Python :: 3.11
Classifier: Programming Language :: Python :: 3.12
Classifier: Programming Language :: Python :: 3.13
Requires-Python: >=3.10
Requires-Dist: anndata<=0.10
Requires-Dist: cellrank>=2.0.1
Requires-Dist: decoupler>=2.1.1
Requires-Dist: deprecated
Requires-Dist: genomepy>=0.16.1
Requires-Dist: moods-python
Requires-Dist: mudata<=0.2.3
Requires-Dist: netgraph
Requires-Dist: pillow<12
Requires-Dist: pooch
Requires-Dist: pyarrow<=20
Requires-Dist: pycirclize<1.10.1
Requires-Dist: pycomplexheatmap>=1.8.2
Requires-Dist: pygam
Requires-Dist: pyranges
Requires-Dist: pysam>=0.23.1
Requires-Dist: pytabix
Requires-Dist: rich>=10
Requires-Dist: scanpy<1.10.4,>=1.9
Requires-Dist: seacells>=0.3.3
Requires-Dist: session-info
Requires-Dist: tensorly
Requires-Dist: torch>=2
Provides-Extra: dev
Requires-Dist: pre-commit; extra == 'dev'
Requires-Dist: twine>=4.0.2; extra == 'dev'
Provides-Extra: doc
Requires-Dist: docutils!=0.18.*,!=0.19.*,>=0.8; extra == 'doc'
Requires-Dist: ipykernel; extra == 'doc'
Requires-Dist: ipython; extra == 'doc'
Requires-Dist: myst-nb>=1.1; extra == 'doc'
Requires-Dist: pandas; extra == 'doc'
Requires-Dist: setuptools; extra == 'doc'
Requires-Dist: sphinx-autodoc-typehints; extra == 'doc'
Requires-Dist: sphinx-book-theme>=1; extra == 'doc'
Requires-Dist: sphinx-copybutton; extra == 'doc'
Requires-Dist: sphinx-design; extra == 'doc'
Requires-Dist: sphinx-tabs; extra == 'doc'
Requires-Dist: sphinx>=4; extra == 'doc'
Requires-Dist: sphinxcontrib-bibtex>=1; extra == 'doc'
Requires-Dist: sphinxcontrib-mermaid; extra == 'doc'
Requires-Dist: sphinxext-opengraph; extra == 'doc'
Provides-Extra: test
Requires-Dist: coverage; extra == 'test'
Requires-Dist: pytest; extra == 'test'
Requires-Dist: tox; extra == 'test'
